<?xml version="1.0" encoding="utf-8"?>
<cms.classpermission>
  <ClassID>
    <CodeName>GCWS.NewsSection</CodeName>
    <GUID>101c89e6-7e5c-402f-9974-6a56c3b20e66</GUID>
    <ObjectType>cms.documenttype</ObjectType>
  </ClassID>
  <PermissionDescription>{$permissiondescription.document.create$}</PermissionDescription>
  <PermissionDisplayInMatrix>True</PermissionDisplayInMatrix>
  <PermissionDisplayName>{$permissionnames.create$}</PermissionDisplayName>
  <PermissionGUID>af01f20b-5728-45b8-8eda-ce2488e48243</PermissionGUID>
  <PermissionName>CreateSpecific</PermissionName>
  <PermissionOrder>3</PermissionOrder>
</cms.classpermission>