<?xml version="1.0" encoding="utf-8"?>
<cms.uielement>
  <ElementCaption>{$general.general$}</ElementCaption>
  <ElementCheckModuleReadPermission>True</ElementCheckModuleReadPermission>
  <ElementDisplayName>{$general.general$}</ElementDisplayName>
  <ElementFromVersion>8.0</ElementFromVersion>
  <ElementGUID>4dac86c2-2dda-41de-916d-e15924dce8f9</ElementGUID>
  <ElementIsCustom>False</ElementIsCustom>
  <ElementIsGlobalApplication>False</ElementIsGlobalApplication>
  <ElementIsMenu>False</ElementIsMenu>
  <ElementName>Forms.General</ElementName>
  <ElementOrder>1</ElementOrder>
  <ElementParentID>
    <CodeName>EditForm</CodeName>
    <GUID>a6dd1aa1-f2db-4dce-9a3e-83780acd4838</GUID>
    <ObjectType>cms.uielement</ObjectType>
    <Parent>
      <CodeName>CMS</CodeName>
      <GUID>ce1a65a0-80dc-4c53-b0e7-bdecf0aa8c02</GUID>
      <ObjectType>cms.resource</ObjectType>
    </Parent>
  </ElementParentID>
  <ElementProperties>
    <data>
      <includejquery>False</includejquery>
      <category_name_header>False</category_name_header>
      <displaybreadcrumbs>False</displaybreadcrumbs>
    </data>
  </ElementProperties>
  <ElementRequiresGlobalAdminPriviligeLevel>False</ElementRequiresGlobalAdminPriviligeLevel>
  <ElementResourceID>
    <CodeName>CMS</CodeName>
    <GUID>ce1a65a0-80dc-4c53-b0e7-bdecf0aa8c02</GUID>
    <ObjectType>cms.resource</ObjectType>
  </ElementResourceID>
  <ElementSize>0</ElementSize>
  <ElementTargetURL>
    <![CDATA[~/CMSModules/Modules/Pages/Class/AlternativeForm/General.aspx?altformid={%EditedObject.FormID|(identity)GlobalAdministrator|(hash)546cc3b26f05e652bc4ed372080643423b62ed533d2f9377a369e0c7ae6c8a71%}&classid={%EditedObject.FormClassID|(identity)GlobalAdministrator|(hash)dce6640c08cc79fbb036162fe0fd21c124a33dfcb5677f49678f5a512157810d%}&moduleid={%EditedObjectParent.ClassResourceID|(identity)GlobalAdministrator|(hash)97ae6286373f19970c2940662ffa05ab1534f20599328a46c10da862519bf5fb%}]]>
  </ElementTargetURL>
  <ElementType>Url</ElementType>
</cms.uielement>